<?xml version="1.0" encoding="UTF-8" standalone="no"?>
<Migrations>
  <Migration EntityType="LVE" Name="Se agregan columnas nuevas a smartbrowser de retenciones" ReleaseNo="" SeqNo="81000160">
    <Step SeqNo="670" StepType="AD">
      <PO AD_Table_ID="53232" Action="I" Record_ID="66790" Table="AD_View_Column">
        <Data AD_Column_ID="84462" Column="UUID">4cb582f4-9dd0-11e9-8514-0242ac140003</Data>
        <Data AD_Column_ID="58095" Column="IsActive">true</Data>
        <Data AD_Column_ID="58096" Column="Created">2019-09-01 12:28:54.653</Data>
        <Data AD_Column_ID="58097" Column="Updated">2019-09-01 12:28:54.653</Data>
        <Data AD_Column_ID="58101" Column="AD_View_Definition_ID">50429</Data>
        <Data AD_Column_ID="58104" Column="Help" isNewNull="true"/>
        <Data AD_Column_ID="58106" Column="ColumnSQL">wh.Subtrahend</Data>
        <Data AD_Column_ID="58105" Column="Name">Subtrahend</Data>
        <Data AD_Column_ID="58107" Column="ColumnName">WH_Subtrahend</Data>
        <Data AD_Column_ID="58102" Column="Description">Subtrahend for Withholding</Data>
        <Data AD_Column_ID="58100" Column="AD_View_Column_ID">66790</Data>
        <Data AD_Column_ID="58093" Column="AD_Client_ID">0</Data>
        <Data AD_Column_ID="58094" Column="AD_Org_ID">0</Data>
        <Data AD_Column_ID="58103" Column="EntityType">WHH</Data>
        <Data AD_Column_ID="58099" Column="UpdatedBy">100</Data>
        <Data AD_Column_ID="58108" Column="AD_View_ID">50155</Data>
        <Data AD_Column_ID="58109" Column="AD_Column_ID">93916</Data>
        <Data AD_Column_ID="58098" Column="CreatedBy">100</Data>
      </PO>
    </Step>
    <Step SeqNo="680" StepType="AD">
      <PO AD_Table_ID="53228" Action="I" Record_ID="66790" Table="AD_View_Column_Trl">
        <Data AD_Column_ID="58042" Column="IsActive">true</Data>
        <Data AD_Column_ID="58043" Column="Created">2019-09-01 12:28:55.349</Data>
        <Data AD_Column_ID="58044" Column="Updated">2019-09-01 12:28:55.349</Data>
        <Data AD_Column_ID="58049" Column="Description">Subtrahend for Withholding</Data>
        <Data AD_Column_ID="58050" Column="Help" isNewNull="true"/>
        <Data AD_Column_ID="58051" Column="IsTranslated">false</Data>
        <Data AD_Column_ID="58052" Column="Name">Subtrahend</Data>
        <Data AD_Column_ID="58047" Column="AD_View_Column_ID">66790</Data>
        <Data AD_Column_ID="58040" Column="AD_Client_ID">0</Data>
        <Data AD_Column_ID="58041" Column="AD_Org_ID">0</Data>
        <Data AD_Column_ID="58045" Column="CreatedBy">100</Data>
        <Data AD_Column_ID="58048" Column="AD_Language">es_MX</Data>
        <Data AD_Column_ID="58046" Column="UpdatedBy">100</Data>
        <Data AD_Column_ID="84463" Column="UUID">4cb74e86-9dd0-11e9-8514-0242ac140003</Data>
      </PO>
    </Step>
    <Step SeqNo="690" StepType="AD">
      <PO AD_Table_ID="53232" Action="I" Record_ID="66791" Table="AD_View_Column">
        <Data AD_Column_ID="58103" Column="EntityType">WHH</Data>
        <Data AD_Column_ID="84462" Column="UUID">4cb955c8-9dd0-11e9-8514-0242ac140003</Data>
        <Data AD_Column_ID="58095" Column="IsActive">true</Data>
        <Data AD_Column_ID="58096" Column="Created">2019-09-01 12:28:55.58</Data>
        <Data AD_Column_ID="58097" Column="Updated">2019-09-01 12:28:55.58</Data>
        <Data AD_Column_ID="58101" Column="AD_View_Definition_ID">50429</Data>
        <Data AD_Column_ID="58104" Column="Help" isNewNull="true"/>
        <Data AD_Column_ID="58106" Column="ColumnSQL">wh.WithholdingRentalRate_ID</Data>
        <Data AD_Column_ID="58105" Column="Name">Withholding Rental Rate</Data>
        <Data AD_Column_ID="58107" Column="ColumnName">WH_WithholdingRentalRate_ID</Data>
        <Data AD_Column_ID="58102" Column="Description" isNewNull="true"/>
        <Data AD_Column_ID="58100" Column="AD_View_Column_ID">66791</Data>
        <Data AD_Column_ID="58093" Column="AD_Client_ID">0</Data>
        <Data AD_Column_ID="58094" Column="AD_Org_ID">0</Data>
        <Data AD_Column_ID="58099" Column="UpdatedBy">100</Data>
        <Data AD_Column_ID="58108" Column="AD_View_ID">50155</Data>
        <Data AD_Column_ID="58109" Column="AD_Column_ID">93834</Data>
        <Data AD_Column_ID="58098" Column="CreatedBy">100</Data>
      </PO>
    </Step>
    <Step SeqNo="700" StepType="AD">
      <PO AD_Table_ID="53228" Action="I" Record_ID="66791" Table="AD_View_Column_Trl">
        <Data AD_Column_ID="58042" Column="IsActive">true</Data>
        <Data AD_Column_ID="58043" Column="Created">2019-09-01 12:28:56.466</Data>
        <Data AD_Column_ID="58044" Column="Updated">2019-09-01 12:28:56.466</Data>
        <Data AD_Column_ID="58049" Column="Description" isNewNull="true"/>
        <Data AD_Column_ID="58050" Column="Help" isNewNull="true"/>
        <Data AD_Column_ID="58051" Column="IsTranslated">false</Data>
        <Data AD_Column_ID="58052" Column="Name">Withholding Rental Rate</Data>
        <Data AD_Column_ID="58047" Column="AD_View_Column_ID">66791</Data>
        <Data AD_Column_ID="58040" Column="AD_Client_ID">0</Data>
        <Data AD_Column_ID="58041" Column="AD_Org_ID">0</Data>
        <Data AD_Column_ID="58045" Column="CreatedBy">100</Data>
        <Data AD_Column_ID="58048" Column="AD_Language">es_MX</Data>
        <Data AD_Column_ID="58046" Column="UpdatedBy">100</Data>
        <Data AD_Column_ID="84463" Column="UUID">4cbb09d6-9dd0-11e9-8514-0242ac140003</Data>
      </PO>
    </Step>
    <Step SeqNo="710" StepType="AD">
      <PO AD_Table_ID="53232" Action="I" Record_ID="66792" Table="AD_View_Column">
        <Data AD_Column_ID="84462" Column="UUID">4cbd2cf2-9dd0-11e9-8514-0242ac140003</Data>
        <Data AD_Column_ID="58095" Column="IsActive">true</Data>
        <Data AD_Column_ID="58096" Column="Created">2019-09-01 12:28:56.656</Data>
        <Data AD_Column_ID="58097" Column="Updated">2019-09-01 12:28:56.656</Data>
        <Data AD_Column_ID="58101" Column="AD_View_Definition_ID">50429</Data>
        <Data AD_Column_ID="58104" Column="Help" isNewNull="true"/>
        <Data AD_Column_ID="58106" Column="ColumnSQL">wh.WithholdingVariableRate_ID</Data>
        <Data AD_Column_ID="58105" Column="Name">Withholding Retal Variable Rate</Data>
        <Data AD_Column_ID="58107" Column="ColumnName">WH_WithholdingVariableRate_ID</Data>
        <Data AD_Column_ID="58102" Column="Description" isNewNull="true"/>
        <Data AD_Column_ID="58100" Column="AD_View_Column_ID">66792</Data>
        <Data AD_Column_ID="58093" Column="AD_Client_ID">0</Data>
        <Data AD_Column_ID="58094" Column="AD_Org_ID">0</Data>
        <Data AD_Column_ID="58103" Column="EntityType">WHH</Data>
        <Data AD_Column_ID="58099" Column="UpdatedBy">100</Data>
        <Data AD_Column_ID="58108" Column="AD_View_ID">50155</Data>
        <Data AD_Column_ID="58109" Column="AD_Column_ID">93835</Data>
        <Data AD_Column_ID="58098" Column="CreatedBy">100</Data>
      </PO>
    </Step>
    <Step SeqNo="720" StepType="AD">
      <PO AD_Table_ID="53228" Action="I" Record_ID="66792" Table="AD_View_Column_Trl">
        <Data AD_Column_ID="58041" Column="AD_Org_ID">0</Data>
        <Data AD_Column_ID="58042" Column="IsActive">true</Data>
        <Data AD_Column_ID="58043" Column="Created">2019-09-01 12:28:57.708</Data>
        <Data AD_Column_ID="58044" Column="Updated">2019-09-01 12:28:57.708</Data>
        <Data AD_Column_ID="58049" Column="Description" isNewNull="true"/>
        <Data AD_Column_ID="58050" Column="Help" isNewNull="true"/>
        <Data AD_Column_ID="58051" Column="IsTranslated">false</Data>
        <Data AD_Column_ID="58052" Column="Name">Withholding Retal Variable Rate</Data>
        <Data AD_Column_ID="58047" Column="AD_View_Column_ID">66792</Data>
        <Data AD_Column_ID="58040" Column="AD_Client_ID">0</Data>
        <Data AD_Column_ID="58045" Column="CreatedBy">100</Data>
        <Data AD_Column_ID="58048" Column="AD_Language">es_MX</Data>
        <Data AD_Column_ID="58046" Column="UpdatedBy">100</Data>
        <Data AD_Column_ID="84463" Column="UUID">4cbef3de-9dd0-11e9-8514-0242ac140003</Data>
      </PO>
    </Step>
    <Step SeqNo="1760" StepType="AD">
      <PO AD_Table_ID="53223" Action="I" Record_ID="65541" Table="AD_Browse_Field">
        <Data AD_Column_ID="63579" Column="IsReadOnly">true</Data>
        <Data AD_Column_ID="57975" Column="IsCentrallyMaintained">true</Data>
        <Data AD_Column_ID="64222" Column="IsOrderBy">false</Data>
        <Data AD_Column_ID="64355" Column="DefaultValue2" isNewNull="true"/>
        <Data AD_Column_ID="64356" Column="DisplayLogic" isNewNull="true"/>
        <Data AD_Column_ID="64358" Column="ReadOnlyLogic" isNewNull="true"/>
        <Data AD_Column_ID="64359" Column="VFormat" isNewNull="true"/>
        <Data AD_Column_ID="64360" Column="ValueMax" isNewNull="true"/>
        <Data AD_Column_ID="64361" Column="ValueMin" isNewNull="true"/>
        <Data AD_Column_ID="67114" Column="Callout" isNewNull="true"/>
        <Data AD_Column_ID="81229" Column="IsInfoOnly">false</Data>
        <Data AD_Column_ID="57961" Column="AD_Client_ID">0</Data>
        <Data AD_Column_ID="57962" Column="AD_Org_ID">0</Data>
        <Data AD_Column_ID="57973" Column="EntityType">WHH</Data>
        <Data AD_Column_ID="57968" Column="AD_Browse_Field_ID">65541</Data>
        <Data AD_Column_ID="57982" Column="SeqNo">110</Data>
        <Data AD_Column_ID="57984" Column="AD_Reference_Value_ID">54152</Data>
        <Data AD_Column_ID="57967" Column="UpdatedBy">100</Data>
        <Data AD_Column_ID="57966" Column="CreatedBy">100</Data>
        <Data AD_Column_ID="63218" Column="Axis_Column_ID" isNewNull="true"/>
        <Data AD_Column_ID="57969" Column="AD_Element_ID">61096</Data>
        <Data AD_Column_ID="57971" Column="AD_View_Column_ID">66792</Data>
        <Data AD_Column_ID="57970" Column="AD_Reference_ID">18</Data>
        <Data AD_Column_ID="57983" Column="AD_Browse_ID">50181</Data>
        <Data AD_Column_ID="63219" Column="Axis_Parent_Column_ID" isNewNull="true"/>
        <Data AD_Column_ID="64221" Column="SortNo" isNewNull="true"/>
        <Data AD_Column_ID="64353" Column="AD_Val_Rule_ID" isNewNull="true"/>
        <Data AD_Column_ID="64357" Column="FieldLength">10</Data>
        <Data AD_Column_ID="78559" Column="SeqNoGrid">0</Data>
        <Data AD_Column_ID="84296" Column="UUID">77f5a30e-a267-11e9-8834-0242ac110003</Data>
        <Data AD_Column_ID="57964" Column="Created">2019-09-01 12:30:03.464</Data>
        <Data AD_Column_ID="57963" Column="IsActive">true</Data>
        <Data AD_Column_ID="57965" Column="Updated">2019-09-01 12:30:03.464</Data>
        <Data AD_Column_ID="57980" Column="IsRange">false</Data>
        <Data AD_Column_ID="57979" Column="IsQueryCriteria">false</Data>
        <Data AD_Column_ID="57985" Column="IsMandatory">false</Data>
        <Data AD_Column_ID="64354" Column="DefaultValue" isNewNull="true"/>
        <Data AD_Column_ID="64853" Column="InfoFactoryClass" isNewNull="true"/>
        <Data AD_Column_ID="57977" Column="IsIdentifier">false</Data>
        <Data AD_Column_ID="57978" Column="IsKey">false</Data>
        <Data AD_Column_ID="57972" Column="Description" isNewNull="true"/>
        <Data AD_Column_ID="57974" Column="Help" isNewNull="true"/>
        <Data AD_Column_ID="57976" Column="IsDisplayed">true</Data>
        <Data AD_Column_ID="57981" Column="Name">Withholding Retal Variable Rate</Data>
      </PO>
    </Step>
    <Step SeqNo="1770" StepType="AD">
      <PO AD_Table_ID="53227" Action="I" Record_ID="0" Table="AD_Browse_Field_Trl">
        <Data AD_Column_ID="84297" Column="UUID">77f7e768-a267-11e9-8834-0242ac110003</Data>
        <Data AD_Column_ID="58029" Column="IsActive">true</Data>
        <Data AD_Column_ID="58030" Column="Created">2019-09-01 12:30:04.661</Data>
        <Data AD_Column_ID="58031" Column="Updated">2019-09-01 12:30:04.661</Data>
        <Data AD_Column_ID="58036" Column="Description">Tasa Variable de I.S.L.R Aplicada al documento</Data>
        <Data AD_Column_ID="58037" Column="Help" isNewNull="true"/>
        <Data AD_Column_ID="58038" Column="IsTranslated">false</Data>
        <Data AD_Column_ID="58039" Column="Name">Tasa Variable de I.S.L.R Aplicada</Data>
        <Data AD_Column_ID="58027" Column="AD_Client_ID">0</Data>
        <Data AD_Column_ID="58028" Column="AD_Org_ID">0</Data>
        <Data AD_Column_ID="58035" Column="AD_Language">es_MX</Data>
        <Data AD_Column_ID="58033" Column="UpdatedBy">100</Data>
        <Data AD_Column_ID="58034" Column="AD_Browse_Field_ID">65541</Data>
        <Data AD_Column_ID="58032" Column="CreatedBy">100</Data>
      </PO>
    </Step>
    <Step SeqNo="1790" StepType="AD">
      <PO AD_Table_ID="53223" Action="I" Record_ID="65542" Table="AD_Browse_Field">
        <Data AD_Column_ID="57962" Column="AD_Org_ID">0</Data>
        <Data AD_Column_ID="57972" Column="Description" isNewNull="true"/>
        <Data AD_Column_ID="57964" Column="Created">2019-09-01 12:30:05.199</Data>
        <Data AD_Column_ID="57963" Column="IsActive">true</Data>
        <Data AD_Column_ID="57965" Column="Updated">2019-09-01 12:30:05.199</Data>
        <Data AD_Column_ID="57980" Column="IsRange">false</Data>
        <Data AD_Column_ID="57979" Column="IsQueryCriteria">false</Data>
        <Data AD_Column_ID="57985" Column="IsMandatory">false</Data>
        <Data AD_Column_ID="64354" Column="DefaultValue" isNewNull="true"/>
        <Data AD_Column_ID="64853" Column="InfoFactoryClass" isNewNull="true"/>
        <Data AD_Column_ID="57977" Column="IsIdentifier">false</Data>
        <Data AD_Column_ID="57978" Column="IsKey">false</Data>
        <Data AD_Column_ID="57974" Column="Help" isNewNull="true"/>
        <Data AD_Column_ID="57976" Column="IsDisplayed">true</Data>
        <Data AD_Column_ID="57981" Column="Name">Withholding Rental Rate</Data>
        <Data AD_Column_ID="63579" Column="IsReadOnly">true</Data>
        <Data AD_Column_ID="57975" Column="IsCentrallyMaintained">true</Data>
        <Data AD_Column_ID="64222" Column="IsOrderBy">false</Data>
        <Data AD_Column_ID="64355" Column="DefaultValue2" isNewNull="true"/>
        <Data AD_Column_ID="64356" Column="DisplayLogic" isNewNull="true"/>
        <Data AD_Column_ID="64358" Column="ReadOnlyLogic" isNewNull="true"/>
        <Data AD_Column_ID="64359" Column="VFormat" isNewNull="true"/>
        <Data AD_Column_ID="64360" Column="ValueMax" isNewNull="true"/>
        <Data AD_Column_ID="64361" Column="ValueMin" isNewNull="true"/>
        <Data AD_Column_ID="67114" Column="Callout" isNewNull="true"/>
        <Data AD_Column_ID="81229" Column="IsInfoOnly">false</Data>
        <Data AD_Column_ID="57961" Column="AD_Client_ID">0</Data>
        <Data AD_Column_ID="57973" Column="EntityType">WHH</Data>
        <Data AD_Column_ID="57968" Column="AD_Browse_Field_ID">65542</Data>
        <Data AD_Column_ID="57982" Column="SeqNo">120</Data>
        <Data AD_Column_ID="57984" Column="AD_Reference_Value_ID">54151</Data>
        <Data AD_Column_ID="57967" Column="UpdatedBy">100</Data>
        <Data AD_Column_ID="57966" Column="CreatedBy">100</Data>
        <Data AD_Column_ID="63218" Column="Axis_Column_ID" isNewNull="true"/>
        <Data AD_Column_ID="57969" Column="AD_Element_ID">61095</Data>
        <Data AD_Column_ID="57971" Column="AD_View_Column_ID">66791</Data>
        <Data AD_Column_ID="57970" Column="AD_Reference_ID">18</Data>
        <Data AD_Column_ID="57983" Column="AD_Browse_ID">50181</Data>
        <Data AD_Column_ID="63219" Column="Axis_Parent_Column_ID" isNewNull="true"/>
        <Data AD_Column_ID="64221" Column="SortNo" isNewNull="true"/>
        <Data AD_Column_ID="64353" Column="AD_Val_Rule_ID" isNewNull="true"/>
        <Data AD_Column_ID="64357" Column="FieldLength">10</Data>
        <Data AD_Column_ID="78559" Column="SeqNoGrid">0</Data>
        <Data AD_Column_ID="84296" Column="UUID">77f08d6a-a267-11e9-8834-0242ac110003</Data>
      </PO>
    </Step>
    <Step SeqNo="1800" StepType="AD">
      <PO AD_Table_ID="53227" Action="I" Record_ID="0" Table="AD_Browse_Field_Trl">
        <Data AD_Column_ID="84297" Column="UUID">77f2ddea-a267-11e9-8834-0242ac110003</Data>
        <Data AD_Column_ID="58029" Column="IsActive">true</Data>
        <Data AD_Column_ID="58030" Column="Created">2019-09-01 12:30:06.308</Data>
        <Data AD_Column_ID="58031" Column="Updated">2019-09-01 12:30:06.308</Data>
        <Data AD_Column_ID="58036" Column="Description">Tasa de Retención de I.S.L.R Aplicada al documento</Data>
        <Data AD_Column_ID="58037" Column="Help" isNewNull="true"/>
        <Data AD_Column_ID="58038" Column="IsTranslated">false</Data>
        <Data AD_Column_ID="58039" Column="Name">Tasa de Retención de I.S.L.R Aplicada</Data>
        <Data AD_Column_ID="58027" Column="AD_Client_ID">0</Data>
        <Data AD_Column_ID="58028" Column="AD_Org_ID">0</Data>
        <Data AD_Column_ID="58035" Column="AD_Language">es_MX</Data>
        <Data AD_Column_ID="58033" Column="UpdatedBy">100</Data>
        <Data AD_Column_ID="58034" Column="AD_Browse_Field_ID">65542</Data>
        <Data AD_Column_ID="58032" Column="CreatedBy">100</Data>
      </PO>
    </Step>
    <Step SeqNo="1850" StepType="AD">
      <PO AD_Table_ID="53223" Action="I" Record_ID="65544" Table="AD_Browse_Field">
        <Data AD_Column_ID="57964" Column="Created">2019-09-01 12:30:08.6</Data>
        <Data AD_Column_ID="57970" Column="AD_Reference_ID">12</Data>
        <Data AD_Column_ID="57983" Column="AD_Browse_ID">50181</Data>
        <Data AD_Column_ID="63219" Column="Axis_Parent_Column_ID" isNewNull="true"/>
        <Data AD_Column_ID="64221" Column="SortNo" isNewNull="true"/>
        <Data AD_Column_ID="64353" Column="AD_Val_Rule_ID" isNewNull="true"/>
        <Data AD_Column_ID="64357" Column="FieldLength">0</Data>
        <Data AD_Column_ID="78559" Column="SeqNoGrid">0</Data>
        <Data AD_Column_ID="84296" Column="UUID">77eb7866-a267-11e9-8834-0242ac110003</Data>
        <Data AD_Column_ID="57963" Column="IsActive">true</Data>
        <Data AD_Column_ID="57965" Column="Updated">2019-09-01 12:30:08.6</Data>
        <Data AD_Column_ID="57980" Column="IsRange">false</Data>
        <Data AD_Column_ID="57979" Column="IsQueryCriteria">false</Data>
        <Data AD_Column_ID="57985" Column="IsMandatory">false</Data>
        <Data AD_Column_ID="64354" Column="DefaultValue" isNewNull="true"/>
        <Data AD_Column_ID="64853" Column="InfoFactoryClass" isNewNull="true"/>
        <Data AD_Column_ID="57977" Column="IsIdentifier">false</Data>
        <Data AD_Column_ID="57978" Column="IsKey">false</Data>
        <Data AD_Column_ID="57972" Column="Description">Subtrahend for Withholding</Data>
        <Data AD_Column_ID="57974" Column="Help" isNewNull="true"/>
        <Data AD_Column_ID="57976" Column="IsDisplayed">false</Data>
        <Data AD_Column_ID="57981" Column="Name">Subtrahend</Data>
        <Data AD_Column_ID="63579" Column="IsReadOnly">true</Data>
        <Data AD_Column_ID="57975" Column="IsCentrallyMaintained">true</Data>
        <Data AD_Column_ID="64222" Column="IsOrderBy">false</Data>
        <Data AD_Column_ID="64355" Column="DefaultValue2" isNewNull="true"/>
        <Data AD_Column_ID="64356" Column="DisplayLogic" isNewNull="true"/>
        <Data AD_Column_ID="64358" Column="ReadOnlyLogic" isNewNull="true"/>
        <Data AD_Column_ID="64359" Column="VFormat" isNewNull="true"/>
        <Data AD_Column_ID="64360" Column="ValueMax" isNewNull="true"/>
        <Data AD_Column_ID="64361" Column="ValueMin" isNewNull="true"/>
        <Data AD_Column_ID="67114" Column="Callout" isNewNull="true"/>
        <Data AD_Column_ID="81229" Column="IsInfoOnly">false</Data>
        <Data AD_Column_ID="57961" Column="AD_Client_ID">0</Data>
        <Data AD_Column_ID="57962" Column="AD_Org_ID">0</Data>
        <Data AD_Column_ID="57973" Column="EntityType">WHH</Data>
        <Data AD_Column_ID="57968" Column="AD_Browse_Field_ID">65544</Data>
        <Data AD_Column_ID="57982" Column="SeqNo">0</Data>
        <Data AD_Column_ID="57984" Column="AD_Reference_Value_ID" isNewNull="true"/>
        <Data AD_Column_ID="57967" Column="UpdatedBy">100</Data>
        <Data AD_Column_ID="57966" Column="CreatedBy">100</Data>
        <Data AD_Column_ID="63218" Column="Axis_Column_ID" isNewNull="true"/>
        <Data AD_Column_ID="57969" Column="AD_Element_ID">61103</Data>
        <Data AD_Column_ID="57971" Column="AD_View_Column_ID">66790</Data>
      </PO>
    </Step>
    <Step SeqNo="1860" StepType="AD">
      <PO AD_Table_ID="53227" Action="I" Record_ID="0" Table="AD_Browse_Field_Trl">
        <Data AD_Column_ID="84297" Column="UUID">77edca8a-a267-11e9-8834-0242ac110003</Data>
        <Data AD_Column_ID="58029" Column="IsActive">true</Data>
        <Data AD_Column_ID="58030" Column="Created">2019-09-01 12:30:10.07</Data>
        <Data AD_Column_ID="58031" Column="Updated">2019-09-01 12:30:10.07</Data>
        <Data AD_Column_ID="58036" Column="Description">Sustraendo para Retención</Data>
        <Data AD_Column_ID="58037" Column="Help">El sustraendo, en una resta, es el segundo de los dos números que intervienen y es la cantidad que debe restarse de la otra.</Data>
        <Data AD_Column_ID="58038" Column="IsTranslated">false</Data>
        <Data AD_Column_ID="58039" Column="Name">Sustraendo</Data>
        <Data AD_Column_ID="58027" Column="AD_Client_ID">0</Data>
        <Data AD_Column_ID="58028" Column="AD_Org_ID">0</Data>
        <Data AD_Column_ID="58035" Column="AD_Language">es_MX</Data>
        <Data AD_Column_ID="58033" Column="UpdatedBy">100</Data>
        <Data AD_Column_ID="58034" Column="AD_Browse_Field_ID">65544</Data>
        <Data AD_Column_ID="58032" Column="CreatedBy">100</Data>
      </PO>
    </Step>
  </Migration>
</Migrations>
